<?xml version="1.0" encoding="UTF-8"?>
<!DOCTYPE suite SYSTEM "http://testng.org/testng-1.0.dtd">
<suite name="Regression Testing">
  <test name="Test">
  <parameter name="browser" value="firefox"/>
    <classes>
         <class name="com.gramLabs.test.HomePageTest"/>
         <class name="com.gramLabs.test.NluModulePageTest"/>
            <class name="com.gramLabs.test.OcrModulePageTest"/>
         <class name="com.gramLabs.test.AudioTranscriptPageTest"/>
    </classes>
  </test> <!-- Test -->
</suite> <!-- Suite -->
